gguf_org/__init__.py
gguf_org/__main__.py
gguf_org-0.0.1.dist-info/LICENSE
gguf_org-0.0.1.dist-info/WHEEL
gguf_org-0.0.1.dist-info/METADATA
gguf_org-0.0.1.dist-info/RECORD
