Metadata-Version: 2.1
Name: gguf-org
Version: 0.0.1
Summary: localhost for gguf.org frontend
Author-email: gguf <info@gguf.us>
Classifier: License :: OSI Approved :: MIT License
Project-URL: Repository, https://github.com/gguf-org/frontend
